pgdbm/__init__.py
pgdbm/__version__.py
pgdbm/core.py
pgdbm/errors.py
pgdbm/migrations.py
pgdbm/monitoring.py
pgdbm/py.typed
pgdbm/testing.py
pgdbm/cli/__init__.py
pgdbm/cli/config.py
pgdbm/cli/main.py
pgdbm/cli/utils.py
pgdbm/cli/commands/__init__.py
pgdbm/cli/commands/db.py
pgdbm/cli/commands/dev.py
pgdbm/cli/commands/generate.py
pgdbm/cli/commands/migrate.py
pgdbm/cli/commands/schema.py
pgdbm/fixtures/__init__.py
pgdbm/fixtures/conftest.py
pgdbm-0.4.0.dist-info/METADATA
pgdbm-0.4.0.dist-info/WHEEL
pgdbm-0.4.0.dist-info/entry_points.txt
pgdbm-0.4.0.dist-info/licenses/LICENSE
pgdbm-0.4.0.dist-info/RECORD
