Metadata-Version: 2.4
Name: pgdbm
Version: 0.4.0
Summary: Production-ready async PostgreSQL utilities with connection pooling, migrations, and testing support
Project-URL: Homepage, https://juanreyero.com/open/pgdbm
Project-URL: Documentation, https://github.com/juanre/pgdbm
Project-URL: Repository, https://github.com/juanre/pgdbm
Project-URL: Issues, https://github.com/juanre/pgdbm/issues
Project-URL: Changelog, https://github.com/juanre/pgdbm/blob/main/CHANGELOG.md
Author-email: Juan Reyero <juan@juanreyero.com>
Maintainer-email: Juan Reyero <juan@juanreyero.com>
License: MIT
License-File: LICENSE
Keywords: async,asyncio,asyncpg,database,migrations,postgresql,testing
Classifier: Development Status :: 4 - Beta
Classifier: Framework :: AsyncIO
Classifier: Intended Audience :: Developers
Classifier: License :: OSI Approved :: MIT License
Classifier: Programming Language :: Python :: 3
Classifier: Programming Language :: Python :: 3.9
Classifier: Programming Language :: Python :: 3.10
Classifier: Programming Language :: Python :: 3.11
Classifier: Programming Language :: Python :: 3.12
Classifier: Programming Language :: Python :: 3.13
Classifier: Topic :: Database
Classifier: Topic :: Software Development :: Libraries :: Python Modules
Classifier: Typing :: Typed
Requires-Python: >=3.9
Requires-Dist: asyncpg>=0.28.0
Requires-Dist: pydantic>=2.0.0
Provides-Extra: cli
Requires-Dist: click>=8.0.0; extra == 'cli'
Requires-Dist: tomli>=2.0.0; (python_full_version < '3.11') and extra == 'cli'
